electrical_power/__init__.py
electrical_power/animate.py
electrical_power/electrical_cables.py
electrical_power/electrical_machines.py
electrical_power/elsweedy_cables.db
electrical_power/motors.db
electrical_power/power_ana.py
electrical_power/sqlite_tools.py
electrical_power-0.1.0.dist-info/licenses/LICENSE
tests/test_electrical_cable.py
electrical_power-0.1.0.dist-info/METADATA
electrical_power-0.1.0.dist-info/WHEEL
electrical_power-0.1.0.dist-info/top_level.txt
electrical_power-0.1.0.dist-info/RECORD
