Metadata-Version: 2.4
Name: electrical_power
Version: 0.1.0
Summary: electrical package for power system,machines, and many more
Author-email: walid <WaliedKSoft@gmail.com>
License-Expression: MIT
Project-URL: Homepage, https://github.com/walied-alkady/electrical_power
Requires-Python: >=3.6
License-File: LICENSE
Requires-Dist: pandas>=1.0
Requires-Dist: numpy>=1.0
Requires-Dist: openpyxl>=1.0
Dynamic: license-file
